reactivity/__init__.py
reactivity/__version__.py
reactivity/env.py
reactivity/flags.py
reactivity/py.typed
reactivity/utils.py
reactivity/computed/__init__.py
reactivity/computed/definitions.py
reactivity/computed/utils.py
reactivity/effect/__init__.py
reactivity/effect/definations.py
reactivity/effect/utils.py
reactivity/effect/vars.py
reactivity/patches/__init__.py
reactivity/patches/json_patch.py
reactivity/reactive/__init__.py
reactivity/reactive/utils.py
reactivity/reactive/vars.py
reactivity/ref/__init__.py
reactivity/ref/definitions.py
reactivity/ref/utils.py
reactivity/watch/__init__.py
pyreactivity-0.0.6.dist-info/LICENSE
pyreactivity-0.0.6.dist-info/METADATA
pyreactivity-0.0.6.dist-info/WHEEL
pyreactivity-0.0.6.dist-info/top_level.txt
pyreactivity-0.0.6.dist-info/RECORD
