Metadata-Version: 2.1
Name: pyreactivity
Version: 0.0.6
Summary: Provide a reactivity system similar to Vue.js for Python.
Home-page: https://pyreactivity.jianmu.org/
Author: Zhaoji Wang
Author-email: hwoam@outlook.com
License: Apache License 2.0
Project-URL: Documentation, https://pyreactivity.jianmu.org/
Project-URL: Repository, https://github.com/frederick-wang/pyreactivity
Project-URL: Changelog, https://github.com/frederick-wang/pyreactivity/blob/main/CHANGELOG.md
Project-URL: Bug Tracker, https://github.com/frederick-wang/pyreactivity/issues
Keywords: reactivity,vue,vuejs
Classifier: Development Status :: 2 - Pre-Alpha
Classifier: Intended Audience :: Developers
Classifier: License :: OSI Approved :: Apache Software License
Classifier: Operating System :: OS Independent
Classifier: Programming Language :: Python :: 3
Classifier: Programming Language :: Python :: 3.6
Classifier: Programming Language :: Python :: 3.7
Classifier: Programming Language :: Python :: 3.8
Classifier: Programming Language :: Python :: 3.9
Classifier: Programming Language :: Python :: 3.10
Classifier: Programming Language :: Python :: 3.11
Classifier: Topic :: Software Development :: Libraries :: Python Modules
Requires-Python: >=3.6
License-File: LICENSE
